<?xml version="1.0" encoding="UTF-8"?>
<!DOCTYPE hibernate-mapping PUBLIC "-//Hibernate/Hibernate Mapping DTD 3.0//EN" "http://hibernate.sourceforge.net/hibernate-mapping-3.0.dtd">
<!-- 
    Mapping file autogenerated by MyEclipse Persistence Tools
-->
<hibernate-mapping>
  <class catalog="db_sis_academica" name="net.uch.matriculaonline.mapping.AcPreRequisitos" table="ac_pre_requisitos">
    <id name="preReqId" type="java.lang.Integer">
      <column name="pre_req_id"/>
      <generator class="assigned"/>
    </id>
    <many-to-one class="net.uch.matriculaonline.mapping.AcPlanCurso" fetch="select" name="acPlanCursoByPlancurIdRequisito">
      <column name="plancur_id_requisito"/>
    </many-to-one>
    <many-to-one class="net.uch.matriculaonline.mapping.AcPlanCurso" fetch="select" name="acPlanCursoByPlancurId">
      <column name="plancur_Id" not-null="true"/>
    </many-to-one>
    <property name="preReqActivo" type="java.lang.String">
      <column length="1" name="pre_req_activo"/>
    </property>
  </class>
</hibernate-mapping>
